sb_on_demand/__init__.py
sb_on_demand/instructions.py
sb_on_demand/oracle_account_data.py
sb_on_demand/oracle_account_data_layout.py
sb_on_demand/oracle_account_utility.py
sb_on_demand/queue_account_data.py
sb_on_demand/queue_account_data_layout.py
sb_on_demand/queue_account_utility.py
sb_on_demand/randomness.py
sb_on_demand/randomness_account_data.py
sb_on_demand/randomness_account_data_layout.py
sb_on_demand/randomness_account_utility.py
sb_on_demand_randomness-1.0.1.dist-info/licenses/LICENCE
sb_on_demand_randomness-1.0.1.dist-info/METADATA
sb_on_demand_randomness-1.0.1.dist-info/WHEEL
sb_on_demand_randomness-1.0.1.dist-info/top_level.txt
sb_on_demand_randomness-1.0.1.dist-info/RECORD
