Metadata-Version: 2.4
Name: sb-on-demand-randomness
Version: 1.0.1
Summary: Switchboard On Demand Randomness Python SDK
Home-page: https://github.com/kingsznhone/sb-on-demand-randomness-py
Author: kingsznhone
License-Expression: MIT
Project-URL: Homepage, https://github.com/kingsznhone/sb-on-demand-randomness-py
Project-URL: Issues, https://github.com/kingsznhone/sb-on-demand-randomness-py/issues
Classifier: Programming Language :: Python :: 3
Classifier: Operating System :: OS Independent
Requires-Python: >=3.8
License-File: LICENCE
Requires-Dist: solders
Requires-Dist: pydantic
Requires-Dist: solana
Dynamic: home-page
Dynamic: license-file
Dynamic: requires-python
